AUTHORS.md
CONTRIBUTING.md
MANIFEST.in
Makefile
NOTICE.md
README.rst
setup.py
./bindings/python/n2.cpp
./src/base.cc
./src/distance.cc
./src/heuristic.cc
./src/hnsw.cc
./src/hnsw_node.cc
./src/mmap.cc
bindings/go/n2.go
bindings/go/n2gomodule.h
bindings/go/n2gomodule.i
bindings/go/n2gomodule_wrap.cxx
bindings/python/n2.pyx
docs/.benchmark.rst.swp
docs/Cpp_API.rst
docs/Go_API.rst
docs/Python_API.rst
docs/benchmark.rst
docs/imgs/build_time/build_time.png
docs/imgs/build_time/build_time_threads.png
docs/imgs/mem/annoy.png
docs/imgs/mem/memory_usage.png
docs/imgs/mem/n2.png
docs/imgs/mem/nmslib.png
docs/imgs/search_time/search_speed.png
docs/imgs/search_time/total.png
include/n2/base.h
include/n2/common.h
include/n2/distance.h
include/n2/heuristic.h
include/n2/hnsw.h
include/n2/hnsw_node.h
include/n2/min_heap.h
include/n2/mmap.h
include/n2/sort.h
n2.egg-info/PKG-INFO
n2.egg-info/SOURCES.txt
n2.egg-info/dependency_links.txt
n2.egg-info/requires.txt
n2.egg-info/top_level.txt
src/Makefile
src/base.cc
src/base.o
src/distance.cc
src/distance.o
src/heuristic.cc
src/heuristic.o
src/hnsw.cc
src/hnsw.o
src/hnsw_node.cc
src/hnsw_node.o
src/mmap.cc
src/mmap.o
tests/cpp_test/Makefile
tests/cpp_test/n2_test.cpp
tests/golang_test/n2_test.go
tests/model/test.n2
tests/python_test/__init__.py
tests/python_test/test_n2.py
tests/python_test/__pycache__/__init__.cpython-36.pyc
tests/python_test/__pycache__/test_n2.cpython-36.pyc
third_party/googletest/.git
third_party/googletest/.gitignore
third_party/googletest/.travis.yml
third_party/googletest/BUILD.bazel
third_party/googletest/CMakeLists.txt
third_party/googletest/README.md
third_party/googletest/WORKSPACE
third_party/googletest/appveyor.yml
third_party/googletest/travis.sh
third_party/googletest/googlemock/CHANGES
third_party/googletest/googlemock/CMakeLists.txt
third_party/googletest/googlemock/CONTRIBUTORS
third_party/googletest/googlemock/LICENSE
third_party/googletest/googlemock/Makefile.am
third_party/googletest/googlemock/README.md
third_party/googletest/googlemock/configure.ac
third_party/googletest/googlemock/build-aux/.keep
