Metadata-Version: 1.1
Name: n2
Version: 0.1.4
Summary: Approximate Nearest Neighbor library
Home-page: UNKNOWN
Author: Kakao.corp
Author-email: recotech.kakao@gmail.com
License: Apache License 2.0
Keywords: Approximate Nearest Neighbor
Platform: UNKNOWN
Classifier: Programming Language :: Python
Classifier: Programming Language :: Python :: 2
Classifier: Programming Language :: Python :: 3
Classifier: Programming Language :: Cython
Classifier: Topic :: Software Development :: Libraries :: Python Modules
